{
  "backupDate": "2025-08-11T14:21:46.247Z",
  "projectName": "Premium Choice Real Estate",
  "description": "Complete project backup with all current settings preserved",
  "structure": {
    "frontend": "Next.js 14 with TypeScript",
    "styling": "Tailwind CSS",
    "database": "MySQL with connection pooling",
    "features": [
      "Real estate project listings",
      "Developer profiles",
      "Article management",
      "AI chat integration",
      "Admin panel",
      "Contact forms",
      "Featured projects display"
    ]
  },
  "currentSettings": {
    "navigation": [
      "Home",
      "Projects",
      "Articles",
      "Contact",
      "Developers",
      "Expert"
    ],
    "databaseConnection": "MySQL with optimized pool settings",
    "apiEndpoints": [
      "/api/projects",
      "/api/developers",
      "/api/articles",
      "/api/expert",
      "/api/admin"
    ],
    "fallbackMechanism": "Test data when database unavailable"
  },
  "lastModified": "2025-08-11T14:21:46.247Z"
}